{
  "default": {
    "searchDefault": "DuckDuckGo",
    "searchOrder": ["DuckDuckGo", "DuckDuckGo (HTML)", "DuckDuckGo (Lite)", "Mojeek", "Mullvad Leta (Brave)", "Mullvad Leta (Google)", "Startpage", "Swisscows", "Wikipedia"],
    "visibleDefaultEngines": [
      "ddg", "ddghtml", "ddglite", "mojeek", "leta-brave", "leta-google", "startpage", "swisscows", "wikipedia"
    ]
  },
  "regionOverrides": {
  },
  "locales": {
    "ach": {
      "default": {
        "visibleDefaultEngines": [
          "ddg", "ddghtml", "ddglite", "mojeek", "leta-brave", "leta-google", "startpage", "swisscows", "wikipedia"
        ]
      }
    },
    "an": {
      "default": {
        "visibleDefaultEngines": [
          "ddg", "ddghtml", "ddglite", "mojeek", "leta-brave", "leta-google", "startpage", "swisscows", "wikipedia-an"
        ]
      }
    },
    "ar": {
      "default": {
        "visibleDefaultEngines": [
          "ddg", "ddghtml", "ddglite", "mojeek", "leta-brave", "leta-google", "startpage", "swisscows", "wikipedia-ar"
        ]
      }
    },
    "as": {
      "default": {
        "visibleDefaultEngines": [
          "ddg", "ddghtml", "ddglite", "mojeek", "leta-brave", "leta-google", "startpage", "swisscows", "wikipedia-as"
        ]
      }
    },
    "ast": {
      "default": {
        "visibleDefaultEngines": [
          "ddg", "ddghtml", "ddglite", "mojeek", "leta-brave", "leta-google", "startpage", "swisscows", "wikipedia-ast"
        ]
      }
    },
    "az": {
      "default": {
        "visibleDefaultEngines": [
          "ddg", "ddghtml", "ddglite", "mojeek", "leta-brave", "leta-google", "startpage", "swisscows", "wikipedia-az"
        ]
      }
    },
    "be": {
      "default": {
        "visibleDefaultEngines": [
          "ddg", "ddghtml", "ddglite", "mojeek", "leta-brave", "leta-google", "startpage", "swisscows", "wikipedia-be"
        ]
      }
    },
    "bg": {
      "default": {
        "visibleDefaultEngines": [
          "ddg", "ddghtml", "ddglite", "mojeek", "leta-brave", "leta-google", "startpage", "swisscows", "wikipedia-bg"
        ]
      }
    },
    "bn": {
      "default": {
        "visibleDefaultEngines": [
          "ddg", "ddghtml", "ddglite", "mojeek", "leta-brave", "leta-google", "startpage", "swisscows", "wikipedia-bn"
        ]
      }
    },
    "bn-BD": {
      "default": {
        "visibleDefaultEngines": [
          "ddg", "ddghtml", "ddglite", "mojeek", "leta-brave", "leta-google", "startpage", "swisscows", "wikipedia-bn"
        ]
      }
    },
    "bn-IN": {
      "default": {
        "visibleDefaultEngines": [
          "ddg", "ddghtml", "ddglite", "mojeek", "leta-brave", "leta-google", "startpage", "swisscows", "wikipedia-bn"
        ]
      }
    },
    "br": {
      "default": {
        "visibleDefaultEngines": [
          "ddg", "ddghtml", "ddglite", "mojeek", "leta-brave", "leta-google", "startpage", "swisscows", "wikipedia-br"
        ]
      }
    },
    "bs": {
      "default": {
        "visibleDefaultEngines": [
          "ddg", "ddghtml", "ddglite", "mojeek", "leta-brave", "leta-google", "startpage", "swisscows", "wikipedia-bs"
        ]
      }
    },
    "ca": {
      "default": {
        "visibleDefaultEngines": [
          "ddg", "ddghtml", "ddglite", "mojeek", "leta-brave", "leta-google", "startpage", "swisscows", "wikipedia-ca"
        ]
      }
    },
    "cak": {
      "default": {
        "visibleDefaultEngines": [
          "ddg", "ddghtml", "ddglite", "mojeek", "leta-brave", "leta-google", "startpage", "swisscows", "wikipedia-es"
        ]
      }
    },
    "cs": {
      "default": {
        "visibleDefaultEngines": [
          "ddg", "ddghtml", "ddglite", "mojeek", "leta-brave", "leta-google", "startpage", "swisscows", "wikipedia-cz"
        ]
      }
    },
    "cy": {
      "default": {
        "visibleDefaultEngines": [
          "ddg", "ddghtml", "ddglite", "mojeek", "leta-brave", "leta-google", "startpage", "swisscows", "wikipedia-cy"
        ]
      }
    },
    "da": {
      "default": {
        "visibleDefaultEngines": [
          "ddg", "ddghtml", "ddglite", "mojeek", "leta-brave", "leta-google", "startpage", "swisscows", "wikipedia-da"
        ]
      }
    },
    "de": {
      "default": {
        "visibleDefaultEngines": [
          "ddg", "ddghtml", "ddglite", "mojeek", "leta-brave", "leta-google", "startpage", "swisscows", "wikipedia-de"
        ]
      }
    },
    "de-AT": {
      "default": {
        "visibleDefaultEngines": [
          "ddg", "ddghtml", "ddglite", "mojeek", "leta-brave", "leta-google", "startpage", "swisscows", "wikipedia-de"
        ]
      }
    },
    "dsb": {
      "default": {
        "visibleDefaultEngines": [
          "ddg", "ddghtml", "ddglite", "mojeek", "leta-brave", "leta-google", "startpage", "swisscows", "wikipedia-dsb"
        ]
      }
    },
    "el": {
      "default": {
        "visibleDefaultEngines": [
          "ddg", "ddghtml", "ddglite", "mojeek", "leta-brave", "leta-google", "startpage", "swisscows", "wikipedia-el"
        ]
      }
    },
    "en-AU": {
      "default": {
        "visibleDefaultEngines": [
          "ddg", "ddghtml", "ddglite", "mojeek", "leta-brave", "leta-google", "startpage", "swisscows", "wikipedia"
        ]
      }
    },
    "en-CA": {
      "default": {
        "visibleDefaultEngines": [
          "ddg", "ddghtml", "ddglite", "mojeek", "leta-brave", "leta-google", "startpage", "swisscows", "wikipedia"
        ]
      }
    },
    "en-IE": {
      "default": {
        "visibleDefaultEngines": [
          "ddg", "ddghtml", "ddglite", "mojeek", "leta-brave", "leta-google", "startpage", "swisscows", "wikipedia"
        ]
      }
    },
    "en-GB": {
      "default": {
        "visibleDefaultEngines": [
          "ddg", "ddghtml", "ddglite", "mojeek", "leta-brave", "leta-google", "startpage", "swisscows", "wikipedia"
        ]
      }
    },
    "en-US": {
      "default": {
        "visibleDefaultEngines": [
          "ddg", "ddghtml", "ddglite", "mojeek", "leta-brave", "leta-google", "startpage", "swisscows", "wikipedia"
        ]
      }
    },
    "en-ZA": {
      "default": {
        "visibleDefaultEngines": [
          "ddg", "ddghtml", "ddglite", "mojeek", "leta-brave", "leta-google", "startpage", "swisscows", "wikipedia"
        ]
      }
    },
    "eo": {
      "default": {
        "visibleDefaultEngines": [
          "ddg", "ddghtml", "ddglite", "mojeek", "leta-brave", "leta-google", "startpage", "swisscows", "wikipedia-eo"
        ]
      }
    },
    "es-AR": {
      "default": {
        "visibleDefaultEngines": [
          "ddg", "ddghtml", "ddglite", "mojeek", "leta-brave", "leta-google", "startpage", "swisscows", "wikipedia-es"
        ]
      }
    },
    "es-CL": {
      "default": {
        "visibleDefaultEngines": [
          "ddg", "ddghtml", "ddglite", "mojeek", "leta-brave", "leta-google", "startpage", "swisscows", "wikipedia-es"
        ]
      }
    },
    "es-ES": {
      "default": {
        "visibleDefaultEngines": [
          "ddg", "ddghtml", "ddglite", "mojeek", "leta-brave", "leta-google", "startpage", "swisscows", "wikipedia-es"
        ]
      }
    },
    "es-MX": {
      "default": {
        "visibleDefaultEngines": [
          "ddg", "ddghtml", "ddglite", "mojeek", "leta-brave", "leta-google", "startpage", "swisscows", "wikipedia-es"
        ]
      }
    },
    "et": {
      "default": {
        "visibleDefaultEngines": [
          "ddg", "ddghtml", "ddglite", "mojeek", "leta-brave", "leta-google", "startpage", "swisscows", "wikipedia-et"
        ]
      }
    },
    "eu": {
      "default": {
        "visibleDefaultEngines": [
          "ddg", "ddghtml", "ddglite", "mojeek", "leta-brave", "leta-google", "startpage", "swisscows", "wikipedia-eu"
        ]
      }
    },
    "fa": {
      "default": {
        "visibleDefaultEngines": [
          "ddg", "ddghtml", "ddglite", "mojeek", "leta-brave", "leta-google", "startpage", "swisscows", "wikipedia-fa"
        ]
      }
    },
    "ff": {
      "default": {
        "visibleDefaultEngines": [
          "ddg", "ddghtml", "ddglite", "mojeek", "leta-brave", "leta-google", "startpage", "swisscows", "wikipedia-fr"
        ]
      }
    },
    "fi": {
      "default": {
        "visibleDefaultEngines": [
          "ddg", "ddghtml", "ddglite", "mojeek", "leta-brave", "leta-google", "startpage", "swisscows", "wikipedia-fi"
        ]
      }
    },
    "fr-BE": {
      "default": {
        "visibleDefaultEngines": [
          "ddg", "ddghtml", "ddglite", "mojeek", "leta-brave", "leta-google", "startpage", "swisscows", "wikipedia-fr"
        ]
      }
    },
    "fr-CA": {
      "default": {
        "visibleDefaultEngines": [
          "ddg", "ddghtml", "ddglite", "mojeek", "leta-brave", "leta-google", "startpage", "swisscows", "wikipedia-fr"
        ]
      }
    },
    "fr-FR": {
      "default": {
        "visibleDefaultEngines": [
          "ddg", "ddghtml", "ddglite", "mojeek", "leta-brave", "leta-google", "startpage", "swisscows", "wikipedia-fr"
        ]
      }
    },
    "fr": {
      "default": {
        "visibleDefaultEngines": [
          "ddg", "ddghtml", "ddglite", "mojeek", "leta-brave", "leta-google", "startpage", "swisscows", "wikipedia-fr"
        ]
      }
    },
    "fy-NL": {
      "default": {
        "visibleDefaultEngines": [
          "ddg", "ddghtml", "ddglite", "mojeek", "leta-brave", "leta-google", "startpage", "swisscows", "wikipedia-fy-NL"
        ]
      }
    },
    "ga-IE": {
      "default": {
        "visibleDefaultEngines": [
          "ddg", "ddghtml", "ddglite", "mojeek", "leta-brave", "leta-google", "startpage", "swisscows", "wikipedia-ga-IE"
        ]
      }
    },
    "gd": {
      "default": {
        "visibleDefaultEngines": [
          "ddg", "ddghtml", "ddglite", "mojeek", "leta-brave", "leta-google", "startpage", "swisscows", "wikipedia-gd"
        ]
      }
    },
    "gl": {
      "default": {
        "visibleDefaultEngines": [
          "ddg", "ddghtml", "ddglite", "mojeek", "leta-brave", "leta-google", "startpage", "swisscows", "wikipedia-gl"
        ]
      }
    },
    "gn": {
      "default": {
        "visibleDefaultEngines": [
          "ddg", "ddghtml", "ddglite", "mojeek", "leta-brave", "leta-google", "startpage", "swisscows", "wikipedia-gn"
        ]
      }
    },
    "gu-IN": {
      "default": {
        "visibleDefaultEngines": [
          "ddg", "ddghtml", "ddglite", "mojeek", "leta-brave", "leta-google", "startpage", "swisscows", "wikipedia-gu"
        ]
      }
    },
    "he": {
      "default": {
        "visibleDefaultEngines": [
          "ddg", "ddghtml", "ddglite", "mojeek", "leta-brave", "leta-google", "startpage", "swisscows", "wikipedia-he"
        ]
      }
    },
    "hi-IN": {
      "default": {
        "visibleDefaultEngines": [
          "ddg", "ddghtml", "ddglite", "mojeek", "leta-brave", "leta-google", "startpage", "swisscows", "wikipedia-hi"
        ]
      }
    },
    "hr": {
      "default": {
        "visibleDefaultEngines": [
          "ddg", "ddghtml", "ddglite", "mojeek", "leta-brave", "leta-google", "startpage", "swisscows", "wikipedia-hr"
        ]
      }
    },
    "hsb": {
      "default": {
        "visibleDefaultEngines": [
          "ddg", "ddghtml", "ddglite", "mojeek", "leta-brave", "leta-google", "startpage", "swisscows", "wikipedia-hsb"
        ]
      }
    },
    "hu": {
      "default": {
        "visibleDefaultEngines": [
          "ddg", "ddghtml", "ddglite", "mojeek", "leta-brave", "leta-google", "startpage", "swisscows", "wikipedia-hu"
        ]
      }
    },
    "hy-AM": {
      "default": {
        "visibleDefaultEngines": [
          "ddg", "ddghtml", "ddglite", "mojeek", "leta-brave", "leta-google", "startpage", "swisscows", "wikipedia-hy-AM"
        ]
      }
    },
    "ia": {
      "default": {
        "visibleDefaultEngines": [
          "ddg", "ddghtml", "ddglite", "mojeek", "leta-brave", "leta-google", "startpage", "swisscows", "wikipedia-ia"
        ]
      }
    },
    "id": {
      "default": {
        "visibleDefaultEngines": [
          "ddg", "ddghtml", "ddglite", "mojeek", "leta-brave", "leta-google", "startpage", "swisscows", "wikipedia-id"
        ]
      }
    },
    "is": {
      "default": {
        "visibleDefaultEngines": [
          "ddg", "ddghtml", "ddglite", "mojeek", "leta-brave", "leta-google", "startpage", "swisscows", "wikipedia-is"
        ]
      }
    },
    "it": {
      "default": {
        "visibleDefaultEngines": [
          "ddg", "ddghtml", "ddglite", "mojeek", "leta-brave", "leta-google", "startpage", "swisscows", "wikipedia-it"
        ]
      }
    },
    "ja": {
      "default": {
        "visibleDefaultEngines": [
          "ddg", "ddghtml", "ddglite", "mojeek", "leta-brave", "leta-google", "startpage", "swisscows", "wikipedia-ja"
        ]
      }
    },
    "ka": {
      "default": {
        "visibleDefaultEngines": [
          "ddg", "ddghtml", "ddglite", "mojeek", "leta-brave", "leta-google", "startpage", "swisscows", "wikipedia-ka"
        ]
      }
    },
    "kab": {
      "default": {
        "visibleDefaultEngines": [
          "ddg", "ddghtml", "ddglite", "mojeek", "leta-brave", "leta-google", "startpage", "swisscows", "wikipedia-kab"
        ]
      }
    },
    "kk": {
      "default": {
        "visibleDefaultEngines": [
          "ddg", "ddghtml", "ddglite", "mojeek", "leta-brave", "leta-google", "startpage", "swisscows", "wikipedia-kk"
        ]
      }
    },
    "km": {
      "default": {
        "visibleDefaultEngines": [
          "ddg", "ddghtml", "ddglite", "mojeek", "leta-brave", "leta-google", "startpage", "swisscows", "wikipedia-km"
        ]
      }
    },
    "kn": {
      "default": {
        "visibleDefaultEngines": [
          "ddg", "ddghtml", "ddglite", "mojeek", "leta-brave", "leta-google", "startpage", "swisscows", "wikipedia-kn"
        ]
      }
    },
    "ko": {
      "default": {
        "visibleDefaultEngines": [
          "ddg", "ddghtml", "ddglite", "mojeek", "leta-brave", "leta-google", "startpage", "swisscows", "wikipedia-ko"
        ]
      }
    },
    "lij": {
      "default": {
        "visibleDefaultEngines": [
          "ddg", "ddghtml", "ddglite", "mojeek", "leta-brave", "leta-google", "startpage", "swisscows", "wikipedia-lij"
        ]
      }
    },
    "lo": {
      "default": {
        "visibleDefaultEngines": [
          "ddg", "ddghtml", "ddglite", "mojeek", "leta-brave", "leta-google", "startpage", "swisscows", "wikipedia-lo"
        ]
      }
    },
    "lt": {
      "default": {
        "visibleDefaultEngines": [
          "ddg", "ddghtml", "ddglite", "mojeek", "leta-brave", "leta-google", "startpage", "swisscows", "wikipedia-lt"
        ]
      }
    },
    "ltg": {
      "default": {
        "visibleDefaultEngines": [
          "ddg", "ddghtml", "ddglite", "mojeek", "leta-brave", "leta-google", "startpage", "swisscows", "wikipedia-ltg"
        ]
      }
    },
    "lv": {
      "default": {
        "visibleDefaultEngines": [
          "ddg", "ddghtml", "ddglite", "mojeek", "leta-brave", "leta-google", "startpage", "swisscows", "wikipedia-lv"
        ]
      }
    },
    "mai": {
      "default": {
        "visibleDefaultEngines": [
          "ddg", "ddghtml", "ddglite", "mojeek", "leta-brave", "leta-google", "startpage", "swisscows", "wikipedia-hi"
        ]
      }
    },
    "meh": {
      "default": {
        "visibleDefaultEngines": [
          "ddg", "ddghtml", "ddglite", "mojeek", "leta-brave", "leta-google", "startpage", "swisscows", "wikipedia-es"
        ]
      }
    },
    "mix": {
      "default": {
        "visibleDefaultEngines": [
          "ddg", "ddghtml", "ddglite", "mojeek", "leta-brave", "leta-google", "startpage", "swisscows", "wikipedia-es"
        ]
      }
    },
    "ml": {
      "default": {
        "visibleDefaultEngines": [
          "ddg", "ddghtml", "ddglite", "mojeek", "leta-brave", "leta-google", "startpage", "swisscows", "wikipedia-ml"
        ]
      }
    },
    "mr": {
      "default": {
        "visibleDefaultEngines": [
          "ddg", "ddghtml", "ddglite", "mojeek", "leta-brave", "leta-google", "startpage", "swisscows", "wikipedia-mr"
        ]
      }
    },
    "ms": {
      "default": {
        "visibleDefaultEngines": [
          "ddg", "ddghtml", "ddglite", "mojeek", "leta-brave", "leta-google", "startpage", "swisscows", "wikipedia-ms"
        ]
      }
    },
    "my": {
      "default": {
        "visibleDefaultEngines": [
          "ddg", "ddghtml", "ddglite", "mojeek", "leta-brave", "leta-google", "startpage", "swisscows", "wikipedia-my"
        ]
      }
    },
    "nb-NO": {
      "default": {
        "visibleDefaultEngines": [
          "ddg", "ddghtml", "ddglite", "mojeek", "leta-brave", "leta-google", "startpage", "swisscows", "wikipedia-NO"
        ]
      }
    },
    "ne-NP": {
      "default": {
        "visibleDefaultEngines": [
          "ddg", "ddghtml", "ddglite", "mojeek", "leta-brave", "leta-google", "startpage", "swisscows", "wikipedia-ne"
        ]
      }
    },
    "nl-NL": {
      "default": {
        "visibleDefaultEngines": [
          "ddg", "ddghtml", "ddglite", "mojeek", "leta-brave", "leta-google", "startpage", "swisscows", "wikipedia-nl"
        ]
      }
    },
    "nl": {
      "default": {
        "visibleDefaultEngines": [
          "ddg", "ddghtml", "ddglite", "mojeek", "leta-brave", "leta-google", "startpage", "swisscows", "wikipedia-nl"
        ]
      }
    },
    "nn-NO": {
      "default": {
        "visibleDefaultEngines": [
          "ddg", "ddghtml", "ddglite", "mojeek", "leta-brave", "leta-google", "startpage", "swisscows", "wikipedia-NN"
        ]
      }
    },
    "oc": {
      "default": {
        "visibleDefaultEngines": [
          "ddg", "ddghtml", "ddglite", "mojeek", "leta-brave", "leta-google", "startpage", "swisscows", "wikipedia-oc"
        ]
      }
    },
    "or": {
      "default": {
        "visibleDefaultEngines": [
          "ddg", "ddghtml", "ddglite", "mojeek", "leta-brave", "leta-google", "startpage", "swisscows", "wikipedia-or"
        ]
      }
    },
    "pa-IN": {
      "default": {
        "visibleDefaultEngines": [
          "ddg", "ddghtml", "ddglite", "mojeek", "leta-brave", "leta-google", "startpage", "swisscows", "wikipedia-pa"
        ]
      }
    },
    "pl": {
      "default": {
        "visibleDefaultEngines": [
          "ddg", "ddghtml", "ddglite", "mojeek", "leta-brave", "leta-google", "startpage", "swisscows", "wikipedia-pl"
        ]
      }
    },
    "pt-BR": {
      "default": {
        "visibleDefaultEngines": [
          "ddg", "ddghtml", "ddglite", "mojeek", "leta-brave", "leta-google", "startpage", "swisscows", "wikipedia-pt"
        ]
      }
    },
    "pt-PT": {
      "default": {
        "visibleDefaultEngines": [
          "ddg", "ddghtml", "ddglite", "mojeek", "leta-brave", "leta-google", "startpage", "swisscows", "wikipedia-pt"
        ]
      }
    },
    "rm": {
      "default": {
        "visibleDefaultEngines": [
          "ddg", "ddghtml", "ddglite", "mojeek", "leta-brave", "leta-google", "startpage", "swisscows", "wikipedia-rm"
        ]
      }
    },
    "ro": {
      "default": {
        "visibleDefaultEngines": [
          "ddg", "ddghtml", "ddglite", "mojeek", "leta-brave", "leta-google", "startpage", "swisscows", "wikipedia-ro"
        ]
      }
    },
    "ru": {
      "default": {
        "visibleDefaultEngines": [
          "ddg", "ddghtml", "ddglite", "mojeek", "leta-brave", "leta-google", "startpage", "swisscows", "wikipedia-ru"
        ]
      }
    },
    "sk": {
      "default": {
        "visibleDefaultEngines": [
          "ddg", "ddghtml", "ddglite", "mojeek", "leta-brave", "leta-google", "startpage", "swisscows", "wikipedia-sk"
        ]
      }
    },
    "sl": {
      "default": {
        "visibleDefaultEngines": [
          "ddg", "ddghtml", "ddglite", "mojeek", "leta-brave", "leta-google", "startpage", "swisscows", "wikipedia-sl"
        ]
      }
    },
    "son": {
      "default": {
        "visibleDefaultEngines": [
          "ddg", "ddghtml", "ddglite", "mojeek", "leta-brave", "leta-google", "startpage", "swisscows", "wikipedia-fr"
        ]
      }
    },
    "sq": {
      "default": {
        "visibleDefaultEngines": [
          "ddg", "ddghtml", "ddglite", "mojeek", "leta-brave", "leta-google", "startpage", "swisscows", "wikipedia-sq"
        ]
      }
    },
    "sr": {
      "default": {
        "visibleDefaultEngines": [
          "ddg", "ddghtml", "ddglite", "mojeek", "leta-brave", "leta-google", "startpage", "swisscows", "wikipedia-sr"
        ]
      }
    },
    "sv-SE": {
      "default": {
        "visibleDefaultEngines": [
          "ddg", "ddghtml", "ddglite", "mojeek", "leta-brave", "leta-google", "startpage", "swisscows", "wikipedia-sv-SE"
        ]
      }
    },
    "ta": {
      "default": {
        "visibleDefaultEngines": [
          "ddg", "ddghtml", "ddglite", "mojeek", "leta-brave", "leta-google", "startpage", "swisscows", "wikipedia-ta"
        ]
      }
    },
    "te": {
      "default": {
        "visibleDefaultEngines": [
          "ddg", "ddghtml", "ddglite", "mojeek", "leta-brave", "leta-google", "startpage", "swisscows", "wikipedia-te"
        ]
      }
    },
    "th": {
      "default": {
        "visibleDefaultEngines": [
          "ddg", "ddghtml", "ddglite", "mojeek", "leta-brave", "leta-google", "startpage", "swisscows", "wikipedia-th"
        ]
      }
    },
    "tl": {
      "default": {
        "visibleDefaultEngines": [
          "ddg", "ddghtml", "ddglite", "mojeek", "leta-brave", "leta-google", "startpage", "swisscows", "wikipedia-tl"
        ]
      }
    },
    "tr": {
      "default": {
        "visibleDefaultEngines": [
          "ddg", "ddghtml", "ddglite", "mojeek", "leta-brave", "leta-google", "startpage", "swisscows", "wikipedia-tr"
        ]
      }
    },
    "trs": {
      "default": {
        "visibleDefaultEngines": [
          "ddg", "ddghtml", "ddglite", "mojeek", "leta-brave", "leta-google", "startpage", "swisscows", "wikipedia-es"
        ]
      }
    },
    "uk": {
      "default": {
        "visibleDefaultEngines": [
          "ddg", "ddghtml", "ddglite", "mojeek", "leta-brave", "leta-google", "startpage", "swisscows", "wikipedia-uk"
        ]
      }
    },
    "ur": {
      "default": {
        "visibleDefaultEngines": [
          "ddg", "ddghtml", "ddglite", "mojeek", "leta-brave", "leta-google", "startpage", "swisscows", "wikipedia-ur"
        ]
      }
    },
    "uz": {
      "default": {
        "visibleDefaultEngines": [
          "ddg", "ddghtml", "ddglite", "mojeek", "leta-brave", "leta-google", "startpage", "swisscows", "wikipedia-uz"
        ]
      }
    },
    "vi": {
      "default": {
        "visibleDefaultEngines": [
          "ddg", "ddghtml", "ddglite", "mojeek", "leta-brave", "leta-google", "startpage", "swisscows", "wikipedia-vi"
        ]
      }
    },
    "wo": {
      "default": {
        "visibleDefaultEngines": [
          "ddg", "ddghtml", "ddglite", "mojeek", "leta-brave", "leta-google", "startpage", "swisscows", "wikipedia-wo"
        ]
      }
    },
    "xh": {
      "default": {
        "visibleDefaultEngines": [
          "ddg", "ddghtml", "ddglite", "mojeek", "leta-brave", "leta-google", "startpage", "swisscows", "wikipedia-xh"
        ]
      }
    },
    "zam": {
      "default": {
        "visibleDefaultEngines": [
          "ddg", "ddghtml", "ddglite", "mojeek", "leta-brave", "leta-google", "startpage", "swisscows", "wikipedia-es"
        ]
      }
    },
    "zh-CN": {
      "default": {
        "visibleDefaultEngines": [
          "ddg", "ddghtml", "ddglite", "mojeek", "leta-brave", "leta-google", "startpage", "swisscows", "wikipedia-zh-CN"
        ]
      }
    },
    "zh-TW": {
      "default": {
        "visibleDefaultEngines": [
          "ddg", "ddghtml", "ddglite", "mojeek", "leta-brave", "leta-google", "startpage", "swisscows", "wikipedia-zh-TW"
        ]
      }
    }
  }
}
